magpie/__init__.py
magpie/coords/__init__.py
magpie/coords/conversions.py
magpie/coords/healpix.py
magpie/coords/polar.py
magpie/coords/usphere.py
magpie/coords/usphere_util.py
magpie/densegrid/__init__.py
magpie/densegrid/box2ring.py
magpie/densegrid/cube2shell.py
magpie/densegrid/heal2ortho.py
magpie/densegrid/heal2polar.py
magpie/densegrid/heal2ring.py
magpie/densegrid/pointofview.py
magpie/montecarlo/__init__.py
magpie/montecarlo/box2ring.py
magpie/montecarlo/cube2shell.py
magpie/montecarlo/heal2polar.py
magpie/montecarlo/heal2ring.py
magpie/one_d/__init__.py
magpie/one_d/one_d.py
magpie/pixels/__init__.py
magpie/pixels/healpix_boundary.py
magpie/pixels/healpix_index.py
magpie/plots/__init__.py
magpie/plots/ortho.py
magpie/plots/shapes.py
magpie/polar/__init__.py
magpie/polar/polar2radial.py
magpie/polar/radial.py
magpie/randoms/__init__.py
magpie/randoms/cart.py
magpie/randoms/pdf.py
magpie/randoms/polar.py
magpie/randoms/sphere.py
magpie/randoms/subsample.py
magpie/randoms/usphere.py
magpie/remap/__init__.py
magpie/remap/grid2grid.py
magpie/shapes/__init__.py
magpie/shapes/shapes.py
magpie/src/__init__.py
magpie/src/remap_1d_grid2grid.cpython-39-darwin.so
magpie/src/remap_2d_grid2grid.cpython-39-darwin.so
magpie/src/remap_3d_grid2grid.cpython-39-darwin.so
magpie/src/remap_utils.cpython-39-darwin.so
magpie/utils/__init__.py
magpie/utils/check.py
magpie/utils/progress.py
magpie_pkg-0.2.1.dist-info/LICENSE.txt
magpie_pkg-0.2.1.dist-info/METADATA
magpie_pkg-0.2.1.dist-info/WHEEL
magpie_pkg-0.2.1.dist-info/top_level.txt
magpie_pkg-0.2.1.dist-info/RECORD
