Metadata-Version: 2.1
Name: magpie-pkg
Version: 0.2.1
Summary: Monte cArlo weiGhted PIxel rEmapping
Home-page: https://github.com/knaidoo29/magpie
Author: Krishna Naidoo
Author-email: krishna.naidoo.11@ucl.ac.uk
License: MIT
Platform: UNKNOWN
Classifier: Development Status :: 5 - Production/Stable
Classifier: Intended Audience :: Developers
Classifier: Intended Audience :: Science/Research
Classifier: Natural Language :: English
Classifier: License :: OSI Approved :: MIT License
Classifier: Programming Language :: Python
Classifier: Topic :: Scientific/Engineering
Classifier: Topic :: Scientific/Engineering :: Astronomy
Classifier: Topic :: Scientific/Engineering :: Mathematics
Requires-Python: >=3
Requires-Dist: numpy
Requires-Dist: matplotlib
Requires-Dist: healpy
